AUTHORS.md
LICENSE.md
README.md
pyproject.toml
setup.cfg
setup.py
sequence/__init__.py
sequence/_version.py
sequence/bathymetry.py
sequence/cli.py
sequence/errors.py
sequence/fluvial.py
sequence/grid.py
sequence/input_reader.py
sequence/logging.py
sequence/netcdf.py
sequence/output_writer.py
sequence/plot.py
sequence/processes.py
sequence/py.typed
sequence/sea_level.py
sequence/sediment_flexure.py
sequence/sequence.py
sequence/sequence_model.py
sequence/shoreline.py
sequence/submarine.py
sequence/subsidence.py
sequence_model.egg-info/PKG-INFO
sequence_model.egg-info/SOURCES.txt
sequence_model.egg-info/dependency_links.txt
sequence_model.egg-info/entry_points.txt
sequence_model.egg-info/requires.txt
sequence_model.egg-info/top_level.txt