Metadata-Version: 2.1
Name: sequence-model
Version: 0.6.0
Summary: Python version of the Steckler Sequence model built with landlab
Author: Eric Hutton
Author-email: mcflugen@gmail.com
Maintainer: Eric Hutton
Maintainer-email: mcflugen@gmail.com
License: MIT
Project-URL: changelog, https://github.com/sequence-dev/sequence/blob/develop/CHANGES.md
Project-URL: documentation, https://sequence.readthedocs.io
Project-URL: homepage, https://github.com/sequence-dev/sequence
Project-URL: repository, https://github.com/sequence-dev/sequence
Keywords: landlab,sequence,stratigraphy
Classifier: Development Status :: 2 - Pre-Alpha
Classifier: Intended Audience :: Science/Research
Classifier: License :: OSI Approved :: MIT License
Classifier: Natural Language :: English
Classifier: Programming Language :: Python :: 3
Classifier: Programming Language :: Python :: 3.10
Classifier: Programming Language :: Python :: 3.11
Classifier: Programming Language :: Python :: 3.12
Requires-Python: >=3.10
License-File: LICENSE.md
License-File: AUTHORS.md
Requires-Dist: compaction
Requires-Dist: landlab
Requires-Dist: netcdf4
Requires-Dist: numpy>=1.22
Requires-Dist: pyyaml
Requires-Dist: rich-click
Requires-Dist: scipy
Requires-Dist: tomlkit
Requires-Dist: tqdm
Provides-Extra: dev
Requires-Dist: nox; extra == "dev"
